README.rst
setup.py
tests/__init__.py
tests/time2words_test.py
time2words/__init__.py
time2words/chain.py
time2words/commands.py
time2words/utils.py
time2words.egg-info/PKG-INFO
time2words.egg-info/SOURCES.txt
time2words.egg-info/dependency_links.txt
time2words.egg-info/requires.txt
time2words.egg-info/top_level.txt
time2words/localization/__init__.py
time2words/localization/_en_us.py