Metadata-Version: 1.0
Name: time2words
Version: 0.1.2
Summary: A Python library for converting numerical representation of time to text.
Home-page: https://github.com/YavorPaunov/time2words
Author: Yavor Paunov
Author-email: hello@yavorpaunov.com
License: MIT
Platform: any
